celery_exporter/__init__.py
celery_exporter/exporter.py
celery_exporter/metrics.py
celery_exporter/thread_collector.py
celery_local_exporter-1.0.dist-info/LICENSE
celery_local_exporter-1.0.dist-info/METADATA
celery_local_exporter-1.0.dist-info/WHEEL
celery_local_exporter-1.0.dist-info/top_level.txt
celery_local_exporter-1.0.dist-info/RECORD
